trollsched/__init__.py
trollsched/boundary.py
trollsched/combine.py
trollsched/compare.py
trollsched/drawing.py
trollsched/graph.py
trollsched/helper_functions.py
trollsched/logger.py
trollsched/pass_scheduling_utils.py
trollsched/satpass.py
trollsched/schedule.py
trollsched/shapefiles_from_schedule.py
trollsched/spherical.py
trollsched/utils.py
trollsched/version.py
trollsched/writers.py
trollsched/tests/__init__.py
trollsched/tests/conftest.py
trollsched/tests/test_pass_outlines.py
trollsched/tests/test_satpass.py
trollsched/tests/test_schedule.py
pytroll_schedule-0.7.5.dist-info/METADATA
pytroll_schedule-0.7.5.dist-info/WHEEL
pytroll_schedule-0.7.5.dist-info/entry_points.txt
pytroll_schedule-0.7.5.dist-info/licenses/LICENSE
pytroll_schedule-0.7.5.dist-info/RECORD
