Metadata-Version: 2.4
Name: pytroll-schedule
Version: 0.7.5
Summary: Scheduling satellite passes in Python
Project-URL: Documentation, https://pytroll-schedule.readthedocs.io/en/latest/
Author-email: The Pytroll Team <pytroll@googlegroups.com>
License: GNU GENERAL PUBLIC LICENSE
License-File: LICENSE
Classifier: Development Status :: 4 - Beta
Classifier: Intended Audience :: Science/Research
Classifier: License :: OSI Approved :: GNU General Public License v3 or later (GPLv3+)
Classifier: Operating System :: OS Independent
Classifier: Programming Language :: Python
Classifier: Topic :: Scientific/Engineering
Classifier: Topic :: Scientific/Engineering :: Astronomy
Requires-Python: >=3.10
Requires-Dist: defusedxml
Requires-Dist: geopandas
Requires-Dist: numpy
Requires-Dist: pandas
Requires-Dist: pyorbital
Requires-Dist: pyresample>=1.22
Requires-Dist: pyyaml
Requires-Dist: shapely
Provides-Extra: doc
Requires-Dist: sphinx; extra == 'doc'
Requires-Dist: sphinx-rtd-theme; extra == 'doc'
Requires-Dist: sphinxcontrib-apidoc; extra == 'doc'
Provides-Extra: test
Requires-Dist: pytest>=8.3.5; extra == 'test'
